{
  "version": "1.1.0",
  "diagrams": [
    {
      "ordinal": 0,
      "scrollPosition": {
        "x": 0,
        "y": 0
      },
      "nodes": [
        {
          "location": {
            "x": 0,
            "y": 0
          },
          "nodeIndex": "IEA-Historical-EV-DATA",
          "nodeLineageTag": "34f536c8-726b-4fa1-a849-841526b5a50c",
          "size": {
            "height": 224,
            "width": 234
          },
          "zIndex": 2
        },
        {
          "location": {
            "x": 428,
            "y": 12
          },
          "nodeIndex": "Date",
          "nodeLineageTag": "1d40b84b-86a8-42ad-9845-b68c40b4371f",
          "size": {
            "height": 200,
            "width": 234
          },
          "zIndex": 1
        }
      ],
      "name": "All tables",
      "zoomValue": 100,
      "pinKeyFieldsToTop": false,
      "showExtraHeaderInfo": false,
      "hideKeyFieldsWhenCollapsed": false,
      "tablesLocked": false
    }
  ],
  "selectedDiagram": "All tables",
  "defaultDiagram": "All tables"
}